LICENSE
README.md
setup.py
pystationapi/Playstation.py
pystationapi/PlaystationEnum.py
pystationapi/PlaystationObject.py
pystationapi/__init__.py
pystationapi.egg-info/PKG-INFO
pystationapi.egg-info/SOURCES.txt
pystationapi.egg-info/dependency_links.txt
pystationapi.egg-info/top_level.txt
tests/__init__.py
tests/test_Playstation.py