Metadata-Version: 2.1
Name: pystationapi
Version: 0.0.1
Summary: Get games from playstation api based on graphql
Home-page: http://pypi.python.org/pypi/pystation-api/
Author: Giacomo Lorenzo
Author-email: giacomolinux@gmail.com
License: Apache License 2.0
Platform: UNKNOWN
License-File: LICENSE
